mtg_mcp/__init__.py
mtg_mcp/__main__.py
mtg_mcp/utils.py
mtg_mcp/tools/__init__.py
mtg_mcp/tools/archidekt.py
mtg_mcp/tools/cardtypes.py
mtg_mcp/tools/combos.py
mtg_mcp/tools/commander.py
mtg_mcp/tools/context.py
mtg_mcp/tools/moxfield.py
mtg_mcp/tools/rules.py
mtg_mcp/tools/ruling.py
mtg_mcp-0.1.3.dist-info/licenses/LICENSE.md
mtg_mcp-0.1.3.dist-info/METADATA
mtg_mcp-0.1.3.dist-info/WHEEL
mtg_mcp-0.1.3.dist-info/entry_points.txt
mtg_mcp-0.1.3.dist-info/top_level.txt
mtg_mcp-0.1.3.dist-info/RECORD
