Metadata-Version: 2.4
Name: mtg-mcp
Version: 0.1.3
Summary: A Model Context Protocol (MCP) server providing comprehensive Magic: The Gathering information for AI assistants
Author-email: wtfregia <wtfregia@users.noreply.github.com>
License: MIT
Project-URL: Homepage, https://github.com/wtfregia/mtg-mcp
Project-URL: Repository, https://github.com/wtfregia/mtg-mcp
Project-URL: Issues, https://github.com/wtfregia/mtg-mcp/issues
Keywords: mcp,magic-the-gathering,mtg,commander,edh,ai
Classifier: Development Status :: 4 - Beta
Classifier: Intended Audience :: Developers
Classifier: License :: OSI Approved :: MIT License
Classifier: Programming Language :: Python :: 3
Classifier: Programming Language :: Python :: 3.12
Classifier: Topic :: Games/Entertainment
Classifier: Topic :: Software Development :: Libraries :: Python Modules
Requires-Python: >=3.12
License-File: LICENSE.md
Requires-Dist: mcp>=1.2.0
Requires-Dist: mtgsdk>=1.3.1
Requires-Dist: aiohttp>=3.8.0
Provides-Extra: test
Requires-Dist: pytest>=7.4.0; extra == "test"
Requires-Dist: pytest-asyncio>=0.21.0; extra == "test"
Requires-Dist: pytest-cov>=4.1.0; extra == "test"
Requires-Dist: pytest-mock>=3.11.1; extra == "test"
Provides-Extra: dev
Requires-Dist: ruff>=0.1.0; extra == "dev"
Dynamic: license-file
